airflow/providers/apache/hdfs/__init__.py
airflow/providers/apache/hdfs/get_provider_info.py
airflow/providers/apache/hdfs/version_compat.py
airflow/providers/apache/hdfs/hooks/__init__.py
airflow/providers/apache/hdfs/hooks/webhdfs.py
airflow/providers/apache/hdfs/log/__init__.py
airflow/providers/apache/hdfs/log/hdfs_task_handler.py
airflow/providers/apache/hdfs/sensors/__init__.py
airflow/providers/apache/hdfs/sensors/web_hdfs.py
apache_airflow_providers_apache_hdfs-4.11.2.dist-info/entry_points.txt
apache_airflow_providers_apache_hdfs-4.11.2.dist-info/licenses/LICENSE
apache_airflow_providers_apache_hdfs-4.11.2.dist-info/licenses/NOTICE
apache_airflow_providers_apache_hdfs-4.11.2.dist-info/WHEEL
apache_airflow_providers_apache_hdfs-4.11.2.dist-info/METADATA
apache_airflow_providers_apache_hdfs-4.11.2.dist-info/RECORD
